docassemble/AssemblyLine/__init__.py
docassemble/AssemblyLine/al_courts.py
docassemble/AssemblyLine/al_document.py
docassemble/AssemblyLine/al_general.py
docassemble/AssemblyLine/custom_jinja_filters.py
docassemble/AssemblyLine/language.py
docassemble/AssemblyLine/py.typed
docassemble/AssemblyLine/requirements.txt
docassemble/AssemblyLine/sessions.py
docassemble/AssemblyLine/sign.py
docassemble/AssemblyLine/test_al_document.py
docassemble/AssemblyLine/test_al_general.py
docassemble/AssemblyLine/test_language.py
docassemble/AssemblyLine/data/questions/al_code.yml
docassemble/AssemblyLine/data/questions/al_document.yml
docassemble/AssemblyLine/data/questions/al_language.yml
docassemble/AssemblyLine/data/questions/al_package.yml
docassemble/AssemblyLine/data/questions/al_package_unstyled.yml
docassemble/AssemblyLine/data/questions/al_question_test.yml
docassemble/AssemblyLine/data/questions/al_reminders.yml
docassemble/AssemblyLine/data/questions/al_saved_sessions.yml
docassemble/AssemblyLine/data/questions/al_saved_sessions_store.yml
docassemble/AssemblyLine/data/questions/al_settings.yml
docassemble/AssemblyLine/data/questions/al_terms_of_use.yml
docassemble/AssemblyLine/data/questions/al_visual.yml
docassemble/AssemblyLine/data/questions/assembly_line.yml
docassemble/AssemblyLine/data/questions/assembly_line_unstyled.yml
docassemble/AssemblyLine/data/questions/demo_search_sessions.yml
docassemble/AssemblyLine/data/questions/feedback.yml
docassemble/AssemblyLine/data/questions/interview_list.yml
docassemble/AssemblyLine/data/questions/ql_baseline.yml
docassemble/AssemblyLine/data/questions/ql_catchall.yml
docassemble/AssemblyLine/data/questions/ql_namechange.yml
docassemble/AssemblyLine/data/questions/reserved_words.yml
docassemble/AssemblyLine/data/questions/test_al_table_document.yml
docassemble/AssemblyLine/data/questions/test_aladdendum.yml
docassemble/AssemblyLine/data/questions/test_alcourts.yml
docassemble/AssemblyLine/data/questions/test_aldocument.yml
docassemble_assemblyline-4.3.0.dist-info/licenses/LICENSE
docassemble_assemblyline-4.3.0.dist-info/METADATA
docassemble_assemblyline-4.3.0.dist-info/WHEEL
docassemble_assemblyline-4.3.0.dist-info/top_level.txt
docassemble_assemblyline-4.3.0.dist-info/RECORD
