Metadata-Version: 2.4
Name: docassemble.AssemblyLine
Version: 4.3.0
Summary: Quickly go from a paper court form to a runnable, guided, step-by-step web application powered by Docassemble. Swap out branding and pre-built questions to meet your needs.
Home-page: https://courtformsonline.org
Author: Suffolk Legal Innovation and Technology Lab
Author-email: Suffolk Legal Innovation and Technology Lab <litlab@suffolk.edu>
License-Expression: MIT
Project-URL: Homepage, https://courtformsonline.org
License-File: LICENSE
Requires-Dist: docassemble.ALToolbox>=0.12.0
Requires-Dist: docassemble.GitHubFeedbackForm>=0.4.1.1
Dynamic: author
Dynamic: home-page
Dynamic: license-file
